LibTest.py
genshin_impact/__init__.py
genshin_impact/gisl.py
genshin_impact/gisl_data.json
genshin_impact-0.1.3.dist-info/METADATA
genshin_impact-0.1.3.dist-info/WHEEL
genshin_impact-0.1.3.dist-info/top_level.txt
genshin_impact-0.1.3.dist-info/RECORD
