Metadata-Version: 2.4
Name: genshin-impact
Version: 0.1.3
Summary: A static library of Genshin item/char info. (WIP)
Author-email: "Imran Bin Gifary (System Delta or Imran Delta Online)" <imran.sdelta@gmail.com>
License: MIT
Project-URL: Homepage, https://github.com/Imran-Delta/GI-Static-Data-Library
Requires-Python: >=3.7
Requires-Dist: packaging
